{
  "_class": "shapeGroup",
  "clippingMaskMode": 0,
  "do_objectID": "8A77454F-72FF-4D2D-BAEE-A4ADA99F449F",
  "exportOptions": {
    "_class": "exportOptions",
    "exportFormats": [
    ],
    "includedLayerIds": [
    ],
    "layerOptions": 0,
    "shouldTrim": false
  },
  "frame": {
    "_class": "rect",
    "constrainProportions": false,
    "do_objectID": "41DD5476-5B36-4E5F-B621-B7E6940D2646",
    "height": 2.714285714285719,
    "width": 2.714285714285701,
    "x": 0,
    "y": 0
  },
  "hasClickThrough": false,
  "hasClippingMask": false,
  "isFlippedHorizontal": false,
  "isFlippedVertical": false,
  "isLocked": false,
  "isVisible": true,
  "layerListExpandedType": 0,
  "layers": [
    {
      "class": "rectangle",
      "id": "2DF2191C-C0E6-4761-A950-E2E6F681BF51"
    }
  ],
  "name": "p",
  "nameIsFixed": false,
  "resizingConstraint": 63,
  "resizingType": 0,
  "rotation": 0,
  "shouldBreakMaskChain": false,
  "style": {
    "_class": "style",
    "blur": {
      "_class": "blur",
      "center": "{0.5, 0.5}",
      "do_objectID": "203CF9E0-B3A4-4A8D-9897-BE5AB51DBF53",
      "isEnabled": false,
      "motionAngle": 0,
      "radius": 3,
      "type": 0
    },
    "do_objectID": "5C2977EB-AA84-446A-BD4C-DB5BC3CDEAE6",
    "endDecorationType": 0,
    "fills": [
      {
        "_class": "fill",
        "color": {
          "_class": "color",
          "alpha": 1,
          "blue": 0,
          "green": 0,
          "red": 0
        },
        "fillType": 0,
        "isEnabled": true,
        "noiseIndex": 0,
        "noiseIntensity": 0,
        "patternFillType": 1,
        "patternTileScale": 1
      }
    ],
    "miterLimit": 10,
    "startDecorationType": 0
  },
  "windingRule": 0
}