{
  "_class": "shapePath",
  "booleanOperation": -1,
  "do_objectID": "EA3552A4-313C-4DFF-966F-30D5926EFCCC",
  "edited": true,
  "exportOptions": {
    "_class": "exportOptions",
    "exportFormats": [
    ],
    "includedLayerIds": [
    ],
    "layerOptions": 0,
    "shouldTrim": false
  },
  "frame": {
    "_class": "rect",
    "constrainProportions": false,
    "do_objectID": "8480C0EB-E15A-469D-9EF7-AAFBFCDCF9F2",
    "height": 6.239999999999998,
    "width": 5.4,
    "x": 41.82000000000042,
    "y": 14.93999999999995
  },
  "isClosed": true,
  "isFlippedHorizontal": false,
  "isFlippedVertical": false,
  "isLocked": false,
  "isVisible": true,
  "layerListExpandedType": 0,
  "name": "Path",
  "nameIsFixed": false,
  "pointRadiusBehaviour": 0,
  "points": [
    {
      "_class": "curvePoint",
      "cornerRadius": 0,
      "curveFrom": "{1, 0.32692307692307671}",
      "curveMode": 1,
      "curveTo": "{1, 0.32692307692307671}",
      "hasCurveFrom": false,
      "hasCurveTo": false,
      "point": "{1, 0.32692307692307671}"
    },
    {
      "_class": "curvePoint",
      "cornerRadius": 0,
      "curveFrom": "{0.10740740740740656, 1}",
      "curveMode": 1,
      "curveTo": "{0.10740740740740656, 1}",
      "hasCurveFrom": false,
      "hasCurveTo": false,
      "point": "{0.10740740740740656, 1}"
    },
    {
      "_class": "curvePoint",
      "cornerRadius": 0,
      "curveFrom": "{0, 0}",
      "curveMode": 1,
      "curveTo": "{0, 0}",
      "hasCurveFrom": false,
      "hasCurveTo": false,
      "point": "{0, 0}"
    },
    {
      "_class": "curvePoint",
      "cornerRadius": 0,
      "curveFrom": "{0.97777777777777275, 0.11217948717948723}",
      "curveMode": 4,
      "curveTo": "{0.9703703703703721, 0.022435897435897079}",
      "hasCurveFrom": true,
      "hasCurveTo": false,
      "point": "{0.9703703703703721, 0.022435897435897079}"
    },
    {
      "_class": "curvePoint",
      "cornerRadius": 0,
      "curveFrom": "{1, 0.32692307692307671}",
      "curveMode": 4,
      "curveTo": "{0.99629629629629124, 0.27243589743589752}",
      "hasCurveFrom": false,
      "hasCurveTo": true,
      "point": "{1, 0.32692307692307671}"
    }
  ],
  "resizingConstraint": 63,
  "resizingType": 0,
  "rotation": 0,
  "shouldBreakMaskChain": false
}