{
  "_class": "group",
  "do_objectID": "06472D22-5617-424C-A5D8-7DC1F7A7134F",
  "exportOptions": {
    "_class": "exportOptions",
    "exportFormats": [
    ],
    "includedLayerIds": [
    ],
    "layerOptions": 0,
    "shouldTrim": false
  },
  "frame": {
    "_class": "rect",
    "constrainProportions": false,
    "do_objectID": "06B0F80B-9683-42DF-8846-F498C0F6804E",
    "height": 3,
    "width": 3,
    "x": 46.14285714285716,
    "y": 0
  },
  "hasClickThrough": false,
  "isFlippedHorizontal": false,
  "isFlippedVertical": false,
  "isLocked": false,
  "isVisible": true,
  "layerListExpandedType": 0,
  "layers": [
    {
      "class": "shapeGroup",
      "id": "5849A148-7829-4B12-81C8-82AE0B5B4F2D"
    }
  ],
  "name": "p-link",
  "nameIsFixed": false,
  "resizingConstraint": 63,
  "resizingType": 0,
  "rotation": 0,
  "shouldBreakMaskChain": false,
  "style": {
    "_class": "style",
    "blur": {
      "_class": "blur",
      "center": "{0.5, 0.5}",
      "do_objectID": "55DBB41D-BC65-401B-8481-E6C8DAF8AD83",
      "isEnabled": false,
      "motionAngle": 0,
      "radius": 3,
      "type": 0
    },
    "do_objectID": "2D3D75E0-2966-4DDB-9104-B7C0FEE81A95",
    "endDecorationType": 0,
    "fills": [
      {
        "_class": "fill",
        "color": {
          "_class": "color",
          "alpha": 1,
          "blue": 0,
          "green": 0,
          "red": 0
        },
        "fillType": 0,
        "isEnabled": true,
        "noiseIndex": 0,
        "noiseIntensity": 0,
        "patternFillType": 1,
        "patternTileScale": 1
      }
    ],
    "miterLimit": 10,
    "startDecorationType": 0
  }
}