{
  "_class": "shapeGroup",
  "clippingMaskMode": 0,
  "do_objectID": "5B3E886D-6818-4C92-9D1B-ABFB6FC4EB82",
  "exportOptions": {
    "_class": "exportOptions",
    "exportFormats": [
    ],
    "includedLayerIds": [
    ],
    "layerOptions": 0,
    "shouldTrim": false
  },
  "frame": {
    "_class": "rect",
    "constrainProportions": true,
    "height": 35,
    "width": 35,
    "x": 0,
    "y": 0
  },
  "hasClickThrough": false,
  "hasClippingMask": false,
  "isFlippedHorizontal": false,
  "isFlippedVertical": false,
  "isLocked": false,
  "isVisible": true,
  "layerListExpandedType": 0,
  "layers": [
    {
      "class": "oval",
      "id": "47097D18-5841-40EC-8DD9-EFEB9565407E"
    }
  ],
  "name": "Oval",
  "nameIsFixed": false,
  "resizingConstraint": 63,
  "resizingType": 0,
  "rotation": 0,
  "shouldBreakMaskChain": false,
  "style": {
    "_class": "style",
    "borders": [
      {
        "_class": "border",
        "color": {
          "_class": "color",
          "alpha": 1,
          "blue": 1,
          "green": 0.8282831075010839,
          "red": 0.6810093118686869
        },
        "fillType": 0,
        "isEnabled": false,
        "position": 0,
        "thickness": 1
      }
    ],
    "endDecorationType": 0,
    "fills": [
      {
        "_class": "fill",
        "color": {
          "_class": "color",
          "alpha": 1,
          "blue": 0.1066960170865059,
          "green": 0.0075132283382118,
          "red": 0.816203773021698
        },
        "fillType": 0,
        "isEnabled": true,
        "noiseIndex": 0,
        "noiseIntensity": 0,
        "patternFillType": 1,
        "patternTileScale": 1
      }
    ],
    "miterLimit": 10,
    "startDecorationType": 0
  },
  "userInfo": {
    "com.animaapp.stc-sketch-plugin": {
      "kModelPropertiesKey": {
        "constraints": {
          "aspectRatio": {
            "constant": 35,
            "enabled": 1,
            "modelID": "constraint_fa7c4316-edc7-4108-9fe2-e4fbbfd881a6",
            "model_class": "ADModelConstraint",
            "model_version": 0.1,
            "multiplier": 35
          },
          "automatic": 1,
          "modelID": "viewConstraints_07ad8ba5-a67d-4bc5-a6b2-9b63febacfe8",
          "model_class": "ADModelViewConstraints",
          "model_version": 0.1,
          "scaleFactor": 1
        }
      }
    }
  },
  "windingRule": 1
}