{
  "_class": "shapePath",
  "booleanOperation": -1,
  "do_objectID": "03184C88-CD9C-4D7C-8172-48937485DDDE",
  "edited": true,
  "exportOptions": {
    "_class": "exportOptions",
    "do_objectID": "41B85104-9539-4D81-ABA9-C8D92311B182",
    "exportFormats": [
    ],
    "includedLayerIds": [
    ],
    "layerOptions": 0,
    "shouldTrim": false
  },
  "frame": {
    "_class": "rect",
    "constrainProportions": false,
    "do_objectID": "2D691BDD-1826-4B2F-A1B4-431DF9A68FE3",
    "height": 3.419999999999998,
    "width": 4.4,
    "x": 17.08000000000027,
    "y": 13.83999999999995
  },
  "isClosed": true,
  "isFlippedHorizontal": false,
  "isFlippedVertical": false,
  "isLocked": false,
  "isVisible": true,
  "layerListExpandedType": 0,
  "name": "Path",
  "nameIsFixed": false,
  "pointRadiusBehaviour": 0,
  "points": [
    {
      "_class": "curvePoint",
      "cornerRadius": 0,
      "curveFrom": "{1, 0.35087719298245623}",
      "curveMode": 1,
      "curveTo": "{1, 0.35087719298245623}",
      "hasCurveFrom": false,
      "hasCurveTo": false,
      "point": "{1, 0.35087719298245623}"
    },
    {
      "_class": "curvePoint",
      "cornerRadius": 0,
      "curveFrom": "{0.75909090909091115, 1}",
      "curveMode": 1,
      "curveTo": "{0.75909090909091115, 1}",
      "hasCurveFrom": false,
      "hasCurveTo": false,
      "point": "{0.75909090909091115, 1}"
    },
    {
      "_class": "curvePoint",
      "cornerRadius": 0,
      "curveFrom": "{0, 0.71345029239766045}",
      "curveMode": 1,
      "curveTo": "{0, 0.71345029239766045}",
      "hasCurveFrom": false,
      "hasCurveTo": false,
      "point": "{0, 0.71345029239766045}"
    },
    {
      "_class": "curvePoint",
      "cornerRadius": 0,
      "curveFrom": "{0.045454545454545456, 0}",
      "curveMode": 1,
      "curveTo": "{0.045454545454545456, 0}",
      "hasCurveFrom": false,
      "hasCurveTo": false,
      "point": "{0.045454545454545456, 0}"
    },
    {
      "_class": "curvePoint",
      "cornerRadius": 0,
      "curveFrom": "{1, 0.35087719298245623}",
      "curveMode": 1,
      "curveTo": "{1, 0.35087719298245623}",
      "hasCurveFrom": false,
      "hasCurveTo": false,
      "point": "{1, 0.35087719298245623}"
    }
  ],
  "resizingConstraint": 63,
  "resizingType": 0,
  "rotation": 0,
  "shouldBreakMaskChain": false
}