{
  "_class": "group",
  "do_objectID": "C1642D8D-4A5C-4114-9337-438B038F3DAF",
  "exportOptions": {
    "_class": "exportOptions",
    "exportFormats": [
    ],
    "includedLayerIds": [
    ],
    "layerOptions": 0,
    "shouldTrim": false
  },
  "frame": {
    "_class": "rect",
    "constrainProportions": false,
    "do_objectID": "7ADDC30E-0933-4C1D-9E9C-3AFAE6F0526F",
    "height": 3,
    "width": 3,
    "x": 16,
    "y": 52
  },
  "hasClickThrough": false,
  "isFlippedHorizontal": false,
  "isFlippedVertical": false,
  "isLocked": false,
  "isVisible": true,
  "layerListExpandedType": 0,
  "layers": [
    {
      "class": "shapeGroup",
      "id": "CBADB1D7-A759-482F-A0AD-FDEAD11FC5A5"
    }
  ],
  "name": "p-link",
  "nameIsFixed": false,
  "resizingConstraint": 63,
  "resizingType": 0,
  "rotation": 0,
  "shouldBreakMaskChain": false,
  "style": {
    "_class": "style",
    "blur": {
      "_class": "blur",
      "center": "{0.5, 0.5}",
      "do_objectID": "AD243AC9-1EF1-4B99-8B65-499A8A3B4A5F",
      "isEnabled": false,
      "motionAngle": 0,
      "radius": 3,
      "type": 0
    },
    "do_objectID": "C3B68657-AD98-47A6-B869-103995A383D3",
    "endDecorationType": 0,
    "fills": [
      {
        "_class": "fill",
        "color": {
          "_class": "color",
          "alpha": 1,
          "blue": 0,
          "green": 0,
          "red": 0
        },
        "fillType": 0,
        "isEnabled": true,
        "noiseIndex": 0,
        "noiseIntensity": 0,
        "patternFillType": 1,
        "patternTileScale": 1
      }
    ],
    "miterLimit": 10,
    "startDecorationType": 0
  }
}