{
  "_class": "shapePath",
  "booleanOperation": -1,
  "do_objectID": "77A388F2-8FE0-447A-A910-1EFAD07724F7",
  "edited": true,
  "exportOptions": {
    "_class": "exportOptions",
    "do_objectID": "4ADE9322-4AF9-4A1C-AC4B-0D9B24856364",
    "exportFormats": [
    ],
    "includedLayerIds": [
    ],
    "layerOptions": 0,
    "shouldTrim": false
  },
  "frame": {
    "_class": "rect",
    "constrainProportions": false,
    "do_objectID": "1A98376A-AEF8-4908-94E2-144741A0908F",
    "height": 4.660000000000003,
    "width": 7.740000000000011,
    "x": 20.29999999999998,
    "y": 38.02000000000006
  },
  "isClosed": true,
  "isFlippedHorizontal": false,
  "isFlippedVertical": false,
  "isLocked": false,
  "isVisible": true,
  "layerListExpandedType": 0,
  "name": "Path",
  "nameIsFixed": false,
  "pointRadiusBehaviour": 0,
  "points": [
    {
      "_class": "curvePoint",
      "cornerRadius": 0,
      "curveFrom": "{0.69509043927648728, 0}",
      "curveMode": 1,
      "curveTo": "{0.69509043927648728, 0}",
      "hasCurveFrom": false,
      "hasCurveTo": false,
      "point": "{0.69509043927648728, 0}"
    },
    {
      "_class": "curvePoint",
      "cornerRadius": 0,
      "curveFrom": "{1, 1}",
      "curveMode": 1,
      "curveTo": "{1, 1}",
      "hasCurveFrom": false,
      "hasCurveTo": false,
      "point": "{1, 1}"
    },
    {
      "_class": "curvePoint",
      "cornerRadius": 0,
      "curveFrom": "{0, 0.4678111587982845}",
      "curveMode": 1,
      "curveTo": "{0, 0.4678111587982845}",
      "hasCurveFrom": false,
      "hasCurveTo": false,
      "point": "{0, 0.4678111587982845}"
    },
    {
      "_class": "curvePoint",
      "cornerRadius": 0,
      "curveFrom": "{0.69509043927648728, 0}",
      "curveMode": 1,
      "curveTo": "{0.69509043927648728, 0}",
      "hasCurveFrom": false,
      "hasCurveTo": false,
      "point": "{0.69509043927648728, 0}"
    }
  ],
  "resizingConstraint": 63,
  "resizingType": 0,
  "rotation": 0,
  "shouldBreakMaskChain": false
}