{
  "_class": "shapePath",
  "booleanOperation": -1,
  "do_objectID": "7ED0ABCE-ECA1-4A8F-AE0B-C4C33089C564",
  "edited": true,
  "exportOptions": {
    "_class": "exportOptions",
    "exportFormats": [
    ],
    "includedLayerIds": [
    ],
    "layerOptions": 0,
    "shouldTrim": false
  },
  "frame": {
    "_class": "rect",
    "constrainProportions": false,
    "do_objectID": "65DE38FE-6D3E-427D-A189-94CB709451FA",
    "height": 5.280000000000002,
    "width": 5.840000000000011,
    "x": 20.34000000000012,
    "y": 16.59999999999999
  },
  "isClosed": true,
  "isFlippedHorizontal": false,
  "isFlippedVertical": false,
  "isLocked": false,
  "isVisible": true,
  "layerListExpandedType": 0,
  "name": "Path",
  "nameIsFixed": false,
  "pointRadiusBehaviour": 0,
  "points": [
    {
      "_class": "curvePoint",
      "cornerRadius": 0,
      "curveFrom": "{1, 0.20833333333333329}",
      "curveMode": 1,
      "curveTo": "{1, 0.20833333333333329}",
      "hasCurveFrom": false,
      "hasCurveTo": false,
      "point": "{1, 0.20833333333333329}"
    },
    {
      "_class": "curvePoint",
      "cornerRadius": 0,
      "curveFrom": "{0.67123287671232845, 1}",
      "curveMode": 1,
      "curveTo": "{0.67123287671232845, 1}",
      "hasCurveFrom": false,
      "hasCurveTo": false,
      "point": "{0.67123287671232845, 1}"
    },
    {
      "_class": "curvePoint",
      "cornerRadius": 0,
      "curveFrom": "{0, 0.7537878787878789}",
      "curveMode": 1,
      "curveTo": "{0, 0.7537878787878789}",
      "hasCurveFrom": false,
      "hasCurveTo": false,
      "point": "{0, 0.7537878787878789}"
    },
    {
      "_class": "curvePoint",
      "cornerRadius": 0,
      "curveFrom": "{0.32876712328767149, 0}",
      "curveMode": 1,
      "curveTo": "{0.32876712328767149, 0}",
      "hasCurveFrom": false,
      "hasCurveTo": false,
      "point": "{0.32876712328767149, 0}"
    },
    {
      "_class": "curvePoint",
      "cornerRadius": 0,
      "curveFrom": "{1, 0.20833333333333329}",
      "curveMode": 1,
      "curveTo": "{1, 0.20833333333333329}",
      "hasCurveFrom": false,
      "hasCurveTo": false,
      "point": "{1, 0.20833333333333329}"
    }
  ],
  "resizingConstraint": 63,
  "resizingType": 0,
  "rotation": 0,
  "shouldBreakMaskChain": false
}